__init__.py
abcjs_interface.py
analyze_degree_of_dissonance_or_atonal.py
analyze_harmonic_states.py
analyze_sauterian_formula.py
calc_harmonies.py
duration.py
preprocess.py
representation.py
to_abc_strings.py
type.py
music_harmony_analysis-1.0.1.dist-info/LICENSE
music_harmony_analysis-1.0.1.dist-info/METADATA
music_harmony_analysis-1.0.1.dist-info/WHEEL
music_harmony_analysis-1.0.1.dist-info/top_level.txt
music_harmony_analysis-1.0.1.dist-info/RECORD
