Metadata-Version: 2.1
Name: music-harmony-analysis
Version: 1.0.1
Summary: Analyze the harmonies in music according to a theory of harmonic perception by Franz Sauter, described in his book 'Tonal music: Anatomy of the Musical Aesthetics'
Author-email: Louis Krüger <louiskrueger2002@gmail.com>
License: MIT License
Project-URL: Homepage, https://notenentwickler.com
Keywords: music,music harmony,music analysis,music theory
Classifier: License :: OSI Approved :: MIT License
Classifier: Programming Language :: Python
Classifier: Programming Language :: Python :: 3
Requires-Python: >=3.10
License-File: LICENSE
Provides-Extra: dev
Requires-Dist: pytest ; extra == 'dev'
